coldstore/__init__.py
coldstore/__main__.py
coldstore/cli/__init__.py
coldstore/cli/app.py
coldstore/core/__init__.py
coldstore/core/archiver.py
coldstore/core/collectors.py
coldstore/core/inspector.py
coldstore/core/manifest.py
coldstore/core/scanner.py
coldstore/core/verifier.py
coldstore/utils/__init__.py
coldstore/utils/formatters.py
coldstore/utils/preview.py
coldstore/utils/progress.py
coldstore-1.0.0.dist-info/METADATA
coldstore-1.0.0.dist-info/WHEEL
coldstore-1.0.0.dist-info/entry_points.txt
coldstore-1.0.0.dist-info/licenses/LICENSE
coldstore-1.0.0.dist-info/RECORD
