Metadata-Version: 2.4
Name: coldstore
Version: 1.0.0
Summary: Project archival with structured metadata (Git state, environment, notes) and multi-level integrity verification
License: MIT
License-File: LICENSE
Keywords: archival,metadata,research,academic,snapshot,verification,git,compliance,audit
Author: Jan Fasnacht
Author-email: jan.fasnacht@gmail.com
Requires-Python: >=3.10,<4.0
Classifier: Development Status :: 5 - Production/Stable
Classifier: Environment :: Console
Classifier: Intended Audience :: Developers
Classifier: Intended Audience :: Science/Research
Classifier: Intended Audience :: System Administrators
Classifier: License :: OSI Approved :: MIT License
Classifier: Operating System :: OS Independent
Classifier: Programming Language :: Python :: 3
Classifier: Programming Language :: Python :: 3.10
Classifier: Programming Language :: Python :: 3.11
Classifier: Programming Language :: Python :: 3.12
Classifier: Programming Language :: Python :: 3.13
Classifier: Programming Language :: Python :: 3.14
Classifier: Topic :: Scientific/Engineering
Classifier: Topic :: Software Development :: Version Control :: Git
Classifier: Topic :: System :: Archiving
Classifier: Topic :: System :: Archiving :: Backup
Classifier: Typing :: Typed
Requires-Dist: click (>=8.0,<8.2)
Requires-Dist: pydantic (>=2.0,<3.0)
Requires-Dist: pyyaml (>=6.0,<7.0)
Requires-Dist: typer (>=0.12.0,<0.13.0)
Project-URL: Documentation, https://github.com/janfasnacht/coldstore#readme
Project-URL: Homepage, https://github.com/janfasnacht/coldstore
Project-URL: Repository, https://github.com/janfasnacht/coldstore
